pynel/__init__.py
pynel/components.py
pynel/config.py
pynel/manager.py
pynel/misc.py
pynel/theme.py
pynel/util.py
pynel-0.1.0.dist-info/METADATA
pynel-0.1.0.dist-info/WHEEL
pynel-0.1.0.dist-info/top_level.txt
pynel-0.1.0.dist-info/RECORD
