Metadata-Version: 2.1
Name: pynel
Version: 0.1.0
Summary: A Minimal clean basic UI for pygame
Author: HussuBro010 (Hussain Vohra)
Author-email: <hussainv2807@gmail.com>
Keywords: python,pygame,python-ui,pygame-ui,minimal,clean,simple
Classifier: Development Status :: 1 - Planning
Classifier: Intended Audience :: Developers
Classifier: Programming Language :: Python :: 3
Classifier: Operating System :: Unix
Classifier: Operating System :: MacOS :: MacOS X
Classifier: Operating System :: Microsoft :: Windows
Requires-Dist: pygame
Requires-Dist: pryttier
Requires-Dist: numpy
